buridan_ui-0.7.6b0.dist-info/licenses/LICENSE.md
cli/__init__.py
cli/main.py
scripts/generate_markdown.py
src/__init__.py
src/export.py
src/hooks.py
src/meta.py
src/routes.py
src/src.py
src/comps/docs/wrapper.py
src/comps/ui/buttons.py
src/comps/ui/themes.py
src/comps/ui/titles.py
src/docs/__init__.py
src/docs/constants.py
src/docs/generator.py
src/docs/parser.py
src/docs/style.py
src/docs/library/__init__.py
src/docs/library/charts/util.py
src/docs/library/charts/area/v1.py
src/docs/library/charts/area/v10.py
src/docs/library/charts/area/v2.py
src/docs/library/charts/area/v3.py
src/docs/library/charts/area/v4.py
src/docs/library/charts/area/v5.py
src/docs/library/charts/area/v6.py
src/docs/library/charts/area/v7.py
src/docs/library/charts/area/v8.py
src/docs/library/charts/area/v9.py
src/docs/library/charts/bar/v1.py
src/docs/library/charts/bar/v10.py
src/docs/library/charts/bar/v2.py
src/docs/library/charts/bar/v3.py
src/docs/library/charts/bar/v4.py
src/docs/library/charts/bar/v5.py
src/docs/library/charts/bar/v6.py
src/docs/library/charts/bar/v7.py
src/docs/library/charts/bar/v8.py
src/docs/library/charts/bar/v9.py
src/docs/library/charts/doughnut/v1.py
src/docs/library/charts/doughnut/v2.py
src/docs/library/charts/line/v1.py
src/docs/library/charts/line/v2.py
src/docs/library/charts/line/v3.py
src/docs/library/charts/line/v4.py
src/docs/library/charts/line/v5.py
src/docs/library/charts/line/v6.py
src/docs/library/charts/line/v7.py
src/docs/library/charts/line/v8.py
src/docs/library/charts/pie/v1.py
src/docs/library/charts/pie/v2.py
src/docs/library/charts/pie/v3.py
src/docs/library/charts/pie/v4.py
src/docs/library/charts/pie/v5.py
src/docs/library/charts/pie/v6.py
src/docs/library/charts/radar/v1.py
src/docs/library/charts/radar/v2.py
src/docs/library/charts/radar/v3.py
src/docs/library/charts/radar/v4.py
src/docs/library/charts/radar/v5.py
src/docs/library/charts/radar/v6.py
src/docs/library/charts/scatter/v1.py
src/docs/library/components/avatar/avatar.py
src/docs/library/components/avatar/examples.py
buridan_ui-0.7.6b0.dist-info/METADATA
buridan_ui-0.7.6b0.dist-info/WHEEL
buridan_ui-0.7.6b0.dist-info/entry_points.txt
buridan_ui-0.7.6b0.dist-info/top_level.txt
buridan_ui-0.7.6b0.dist-info/RECORD
