Metadata-Version: 2.4
Name: buridan-ui
Version: 0.7.6b0
Summary: Buridan UI – A Reflex-based UI component library
Author-email: Ahmad Al Hakim <ahmad@reflex.dev>
Requires-Python: >=3.11
License-File: LICENSE.md
Requires-Dist: reflex>=0.8.15
Requires-Dist: pre-commit>=4.2.0
Requires-Dist: black>=25.1.0
Requires-Dist: typer>=0.12.3
Requires-Dist: buridan-ui>=0.7.5b0
Dynamic: license-file
